merlintf/__init__.py
merlintf/complex.py
merlintf/utils.py
merlintf/keras/__init__.py
merlintf/keras/constraints.py
merlintf/keras/losses.py
merlintf/keras/utils.py
merlintf/keras/layers/__init__.py
merlintf/keras/layers/common.py
merlintf/keras/layers/complex_act.py
merlintf/keras/layers/complex_avgpool.py
merlintf/keras/layers/complex_bn.py
merlintf/keras/layers/complex_cg.py
merlintf/keras/layers/complex_init.py
merlintf/keras/layers/complex_maxpool.py
merlintf/keras/layers/complex_norm.py
merlintf/keras/layers/complex_pad.py
merlintf/keras/layers/data_consistency.py
merlintf/keras/layers/fft.py
merlintf/keras/layers/mri.py
merlintf/keras/layers/warp.py
merlintf/keras/layers/convolutional/__init__.py
merlintf/keras/layers/convolutional/complex_conv.py
merlintf/keras/layers/convolutional/complex_conv2dt.py
merlintf/keras/layers/convolutional/complex_conv3dt.py
merlintf/keras/layers/convolutional/complex_convolutional.py
merlintf/keras/layers/convolutional/complex_convolutional_realkernel.py
merlintf/keras/layers/convolutional/complex_padconv.py
merlintf/keras/layers/convolutional/complex_padconv_2dt.py
merlintf/keras/layers/convolutional/complex_padconv_3dt.py
merlintf/keras/layers/convolutional/complex_padconv_realkernel.py
merlintf/keras/layers/convolutional/conv2dt.py
merlintf/keras/layers/convolutional/conv3dt.py
merlintf/keras/layers/convolutional/padconv.py
merlintf/keras/models/__init__.py
merlintf/keras/models/cnn.py
merlintf/keras/models/foe.py
merlintf/keras/models/unet.py
merlintf/keras/optimizers/__init__.py
merlintf/keras/optimizers/blockadam.py
merlintf/keras/optimizers/optimizers.py
merlintf/optim/BlockAdam.py
merlintf/optim/__init__.py
merlintf/test/__init__.py
merlintf/test/test_layers_complex_act.py
merlintf/test/test_layers_complex_avgpool.py
merlintf/test/test_layers_complex_bn.py
merlintf/test/test_layers_complex_maxpool.py
merlintf/test/test_layers_complex_norm.py
merlintf/test/test_layers_convolutional.py
merlintf_mri-0.4.3.dist-info/METADATA
merlintf_mri-0.4.3.dist-info/WHEEL
merlintf_mri-0.4.3.dist-info/top_level.txt
merlintf_mri-0.4.3.dist-info/RECORD
