Metadata-Version: 2.1
Name: merlintf-mri
Version: 0.4.3
Summary: Machine Enhanced Reconstruction Learning and Interpretation Networks (MERLIN) - merlintf
Home-page: https://github.com/midas-tum/merlin
Author: Kerstin Hammernik, Thomas Kuestner
Author-email: merlin.midastum@gmail.com
License: MIT
Classifier: Programming Language :: Python :: 3 :: Only
Classifier: License :: OSI Approved :: MIT License
Classifier: Operating System :: OS Independent
Classifier: Topic :: Scientific/Engineering :: Artificial Intelligence
Classifier: Topic :: Scientific/Engineering :: Medical Science Apps.
Requires-Dist: numpy >=1.15
Requires-Dist: tensorflow >=2.4
Requires-Dist: tensorflow-addons[tensorflow]
Requires-Dist: pkgconfig
Requires-Dist: h5py
